{
    "personal_info": {
        "name": "刘睿博",
        "age": 26,
        "location": "广州",
        "email": "rl3233@columbia.edu",
        "address": "广东省广州市海珠区",
        "photo":"myprofile.jpg"
    },
    "education": [
        {
            "degree": "硕士",
            "major": "机械工程，机器人与控制方向",
            "school": "哥伦比亚大学 (Columbia University)",
            "graduation_date": "2023.02",
            "gpa": "3.83/4.0"
        },
        {
            "degree": "学士",
            "major": "机械工程",
            "school": "加州大学洛杉矶分校 (University of California Los Angeles)",
            "graduation_date": "2021.06",
            "gpa": "3.68/4.0"
        }
    ],
    "experience": [
        {
            "position": "研发工程师",
            "company": "中国科学院广州软件应用技术研究院",
            "date": "2023.04 - 2024.08",
            "project": [
                {
                    "name":"童园科技项目 - 中学AI实验评分系统",
                    "date":"2023.12 - 2024.06",
                    "details":[
                        "根据深圳市初中物化生实验规范与要求，提出评分算法基础框架，制定共15个符合考试标准的人工智能评分准则，实现基于多路视频物体识别与动作识别的AI评分算法",
                        "针对实际部署场景的设备不同，实现自适应评分框架的设计，满足用户自行设定评分细节与分数设置等信息",
                        "负责编写基于以上评分标准的计算机视觉评分算法，实现基于物体、动作的识别评分算法，在可靠识别情况下实现90%以上评分准确率",
                        "负责计算机视觉识别模型的数据库维护与训练数据的前后处理相关流程，使用超过10万以上自主数据标注图片数据进行模型的训练与优化，在实验室光线条件下实现90%以上识别准确率",
                        "支持该项目在重庆教育装备展，四川内江与内蒙古等地学校成功部署"
                    ]
                },
                {
                    "name": "城市智慧灯杆精准运维项目",
                    "date": "2023.05 - 2023.12",
                    "details": [
                        "基于于亚厂商平台与广州市南沙区政务数据平台对超过1万个以上的智慧路灯运行情况进行以每日为单位的数据处理，并基于降维可视化数据分析对数据进行分析",
                        "利用机器学习与深度学习算法，如LSTM，决策树等模型针对以上路灯故障情况进行建模预测，在通讯稳定情况下达到90%以上故障预测准确率",
                        "搭建多模型协作的一整套数据清洗，分析，建模，预测流程；有效降低传统模式下人工巡查的成本"
                    ]
                },
                {
                    "name": "亲声陪伴 - 基于大模型的数字虚拟人APP",
                    "date": "2023.05 - 2023.07",
                    "details": [
                        "收集针对不同数据人形象的图片数据，并对图片与标注进行清洗，以提升模型学习质量",
                        "基于Stable Diffusion 模型进行参数微调以训练针对用户自定义形象的LORA模型",
                        "基于文字转语音技术，利用大模型API接口生成的文本信息输出为语音信息",
                        "基于深度学习模型实现图片虚拟人口型与语音输出的基本匹配,并在A800服务器上实现低延迟的人机对话",
                        "参加企业内项目年度路演，负责产品整体介绍与演示说明"
                    ]
                }
            ]
        }
    ],

    "project_experience":[
        {
            "from": "哥伦比亚大学 Creative Machines Lab",
            "date": "2022.05 – 2023.02",
            "project":[
                {
                    "name":"整理桌面机械臂课题",       
                    "details": [
                    "改进 WidowX 200机械臂的抓手与底座设计，创建URDF模型",
                    "编写 Socket 程序实现机器人与 PyBullet 模拟器的通讯以达至在模拟环境与现实环境中机械臂的同步运行",
                    "使用 Python 编写脚本用以收集 10 万余张包含不同形状、数量与位姿的物块在桌面上的图像数据，并通过OpenCV 库进行图像的处理以配合深度学习的数据需要",
                    "修改和训练 yolov7 与 Resnet 模型准确识别出一张图片上不同位姿与数量的乐高方块，用于规划机械臂抓取路径",
                    "设计小型神经网络配合笛卡尔控制改善现实环境下机械臂运行的误差，使机械臂的抓取准确率获得显著提升",
                    "与导师共同接受来自纽约时报的采访，负责介绍这个机械臂的课题与展示机械臂运动流程"
                    ]
                },
                {
                    "name":"四足 Self-Model 机器人",
                    "details":[
                        "使用 Python 编写自动生成不同形态机器人模型的脚本，并检测生成的机器人模型能否实现站立与行走",
                        "利用基因算法研究不同形态下机器人的步态,以及探索在不同地形摩檫力下的机器人运动形态",
                        "改进机器人内部电路设计以解决伺服电机过热问题",
                        "运用 Domain Randomization 方法以缩小模拟器到现实的误差，并成功指令实体机器人完成实际行走",
                        "编写 Socket 程序实现机器人与 IMU 及电脑的通讯收集实体机器人的步态数据，并用于神经网络的训练"
                    ]
                }
            ]
        },
        {
            "from":"课程：Robotic Studio, 哥伦比亚大学",
            "date":"2022.01 - 2022.05",
            "project":[
                {
                "name":"双足兔子 机器人",
                "details":[
                    "利用Solidworks绘制机器人3D模型，3D打印后组装电路与机器人，并测试其步态稳定性和能量损耗",
                    "在PyBullet模拟器上构建机器人的模型，并利用机械学习优化其步态，同时使用树莓派与电脑主机连接，远程控制机器人，将机器人的行走速度从3cm/s提升到15 cm/s"
                ]
                }
            ]
        },
        {
            "from":"课程：Machine Design, 加州大学洛杉矶分校",
            "date":"2021.01 - 2021.06",
            "project":[
                {
                "name":"全自动衣柜机器人",
                "details":[
                    "利用Solidworks设计可以承载不同重量与款式衣物的衣柜机器人模型",
                    "设计一款齿轮机构可以仅使用一个电机驱动四个用于处理衣物的机械连杆, 实现衣物的收纳与送出功能",
                    "Solidworks的仿真系统模拟机器人的结构受力情况，并根据仿真情况调整设计"
                ]
                }
            ]
        },
        {
            "from":"设计·建造·飞行俱乐部 Design Build Fly Club, UCLA",
            "date":"2019.10 - 2020.02",
            "project":[
                {
                "name":"遥控飞机模型",
                "details":[
                    "使用 SolidWorks 模拟机翼周围的空气动力，优化飞机模型平面的设计",
                    "测试不同的机翼规格和设计；定义测试结果的规模，监督并测试全过程，最终提高了整体航空电子的性能",
                    "利用 3D 打印、激光切割、数控机床等技术建造飞机部件，并参与飞机的拼装工作"
                ]
                }
            ]
        }
    ],

    "internship":[
        {
        "position": "实习机械工程师",
        "company": "Qt品创科技公司 | 北京，中国",
        "date": "2018.07 – 2018.09",
        "responsibilities": [
            "为公司的机器人项目审查CAD工程图",
            "监督机器人组装过程，对组装后的原型进行质量控制",
            "参与绳索机器人的测试，提供技术建议并记录测试过程和结果"
            ]
        },
        {
        "position": "实习生",
        "company": "广东省博物馆| 广州，中国",
        "date": "2017.07 – 2017.10",
        "responsibilities": [
            "策划并开展青少年传统文化体验项目，制定活动内容与活动预算",
            "设计博物馆内园区的游览项目规划以及使用 Autocad 和 Photoshop 制作地图和游览手册",
            "带领超过 20 名参与夏令营活动的小朋友利用乐高搭建传统中国建筑和交通工具（沙面历史建筑与广船）"
            ]
        }
    ],

    "skills": {
        "software": [
            "Python",
            "C++",
            "Matlab",
            "R Studio",
            "Microsoft office"
        ],
        "engineering_drawing": [
            "AutoCAD",
            "JLCEDA",
            "SolidWorks",
            "SolidCam",
            "OpenCAD"
        ],
        "languages": [
            "普通话（精通）",
            "粤语（精通）",
            "英语（精通）"
        ],
        "others": {
            "name":"广东省博物馆外语组讲解志愿者",
            "description": "在2023-2024年完成超过110小时志愿时长，负责超过10场广东省历史文化展厅全英文讲解以及超过4000字的英文论文翻译工作"
        }
    }
}